ray_embedding/__init__.py
ray_embedding/deploy.py
ray_embedding/dto.py
ray_embedding/embedding_model.py
ray_embedding-1.0.0.dist-info/METADATA
ray_embedding-1.0.0.dist-info/WHEEL
ray_embedding-1.0.0.dist-info/top_level.txt
ray_embedding-1.0.0.dist-info/RECORD
