Metadata-Version: 2.4
Name: ray-embedding
Version: 1.0.0
Summary: "Deploy SentenceTransformers models  Ray-based embedding service with SentenceTransformers"
Author: Crispin Almodovar
Author-email: crispin.almodovar@docorto.ai
Classifier: Programming Language :: Python :: 3
Classifier: License :: OSI Approved :: MIT License
Classifier: Operating System :: OS Independent
Requires-Python: >=3.12
